README.txt
bootstrap.py
buildout.cfg
setup.py
docs/Makefile
docs/api.txt
docs/changes.txt
docs/conf.py
docs/description.txt
docs/development.txt
docs/index.txt
docs/installation.txt
docs/license.txt
docs/make.bat
docs/use.txt
execute/__init__.py
execute.egg-info/PKG-INFO
execute.egg-info/SOURCES.txt
execute.egg-info/dependency_links.txt
execute.egg-info/not-zip-safe
execute.egg-info/requires.txt
execute.egg-info/top_level.txt
execute/tests/__init__.py
execute/tests/test_both.py
execute/tests/test_docs.py
execute/tests/test_returncode.py
execute/tests/test_simple.py