Metadata-Version: 1.0
Name: execute
Version: 1.2
Summary: Common patterns for executing commands as sub processes
Home-page: http://packages.python.org/execute
Author: Chris Withers
Author-email: chris@simplistix.co.uk
License: MIT
Platform: UNKNOWN
Classifier: Development Status :: 5 - Production/Stable
Classifier: Intended Audience :: Developers
Classifier: License :: OSI Approved :: MIT License
